porcupine/__init__.py
porcupine/base.py
porcupine/version.py
porcupine_python-0.6.0.dist-info/LICENCE.md
porcupine_python-0.6.0.dist-info/METADATA
porcupine_python-0.6.0.dist-info/WHEEL
porcupine_python-0.6.0.dist-info/top_level.txt
porcupine_python-0.6.0.dist-info/RECORD
