Metadata-Version: 2.1
Name: porcupine-python
Version: 0.6.0
Summary: A library designed primarily for serializing objects using type checking and resolvers.
Home-page: https://github.com/zurek11/simple_serializer
Author: Adam Žúrek
Author-email: adamzurek14@gmail.com
License: MIT
Classifier: Development Status :: 4 - Beta
Classifier: Programming Language :: Python
Classifier: Programming Language :: Python :: 3.9
Classifier: Programming Language :: Python :: 3.10
Classifier: Programming Language :: Python :: 3.11
Classifier: Programming Language :: Python :: 3 :: Only
Classifier: Programming Language :: Python :: Implementation :: PyPy
Classifier: Intended Audience :: Developers
Classifier: License :: OSI Approved :: MIT License
Classifier: Topic :: Software Development :: Libraries
License-File: LICENCE.md
Requires-Dist: pydantic ==1.*
